<annotation>
	<folder>frames</folder>
	<filename>output_0239.png</filename>
	<path>/home/g0d3lett/Documents/FNP/frames/output_0239.png</path>
	<source>
		<database>Unknown</database>
	</source>
	<size>
		<width>640</width>
		<height>360</height>
		<depth>3</depth>
	</size>
	<segmented>0</segmented>
	<object>
		<name>alpha</name>
		<pose>Unspecified</pose>
		<truncated>0</truncated>
		<difficult>0</difficult>
		<bndbox>
			<xmin>61</xmin>
			<ymin>247</ymin>
			<xmax>87</xmax>
			<ymax>267</ymax>
		</bndbox>
	</object>
	<object>
		<name>alpha</name>
		<pose>Unspecified</pose>
		<truncated>0</truncated>
		<difficult>0</difficult>
		<bndbox>
			<xmin>414</xmin>
			<ymin>141</ymin>
			<xmax>437</xmax>
			<ymax>156</ymax>
		</bndbox>
	</object>
</annotation>
