<annotation>
	<folder>frames</folder>
	<filename>output_1041.png</filename>
	<path>/home/g0d3lett/Documents/FNP/frames/output_1041.png</path>
	<source>
		<database>Unknown</database>
	</source>
	<size>
		<width>640</width>
		<height>360</height>
		<depth>3</depth>
	</size>
	<segmented>0</segmented>
	<object>
		<name>alpha</name>
		<pose>Unspecified</pose>
		<truncated>0</truncated>
		<difficult>0</difficult>
		<bndbox>
			<xmin>502</xmin>
			<ymin>104</ymin>
			<xmax>531</xmax>
			<ymax>120</ymax>
		</bndbox>
	</object>
	<object>
		<name>alpha</name>
		<pose>Unspecified</pose>
		<truncated>0</truncated>
		<difficult>0</difficult>
		<bndbox>
			<xmin>257</xmin>
			<ymin>306</ymin>
			<xmax>281</xmax>
			<ymax>333</ymax>
		</bndbox>
	</object>
</annotation>
